Metadata-Version: 2.1
Name: fastruct
Version: 0.1.1.dev2
Summary: Structural analysis and design made fast and simple
Author-email: Matías Glasner <mglasner10@gmail.com>
License: MIT License
Project-URL: source, https://github.com/mglasner/fastruct
Keywords: python,engineering,structural engineering,seismic,structural design,command line application,cli
Classifier: Intended Audience :: Science/Research
Classifier: License :: OSI Approved :: MIT License
Classifier: Natural Language :: English
Classifier: Operating System :: OS Independent
Classifier: Programming Language :: Python :: 3.11
Classifier: Topic :: Scientific/Engineering
Requires-Python: >=3.11
License-File: LICENSE
Requires-Dist: typer[all] ==0.9.0
Requires-Dist: sqlalchemy ==2.0.20
Provides-Extra: dev
Requires-Dist: pytest ; extra == 'dev'
Requires-Dist: Black ; extra == 'dev'
Requires-Dist: Ruff ; extra == 'dev'
